mwprop/__init__.py
mwprop/get_constants_waveprop_astropy_version.py
mwprop/get_constants_waveprop_scipy_version.py
mwprop/ne2001p/NE2001.py
mwprop/ne2001p/README_NE2001p.txt
mwprop/ne2001p/__init__.py
mwprop/ne2001p/config_ne2001p.py
mwprop/ne2001p/density_components.py
mwprop/ne2001p/density_ne2001.py
mwprop/ne2001p/dmdsm_ne2001p.py
mwprop/ne2001p/ne2001p_input.py
mwprop/ne2001p/ne_arms_ne2001p.py
mwprop/ne2001p/ne_lism.py
mwprop/ne2001p/neclumpN_NE2001_fast.py
mwprop/ne2001p/nevoidN_NE2001.py
mwprop/ne2001p/params/gal01.inp
mwprop/ne2001p/params/ne_arms_log_mod.inp
mwprop/ne2001p/params/ne_gc.inp
mwprop/ne2001p/params/neclumpN.NE2001.dat
mwprop/ne2001p/params/nelism.inp
mwprop/ne2001p/params/nevoidN.NE2001.dat
mwprop/scattering_functions/__init__.py
mwprop/scattering_functions/iss_mw_utils2020p_mod.py
mwprop/scattering_functions/scattering_functions2020.py
mwprop/scattering_functions/taudm_mw_pulsars.py
mwprop-1.0.10.data/scripts/NE2001p.py
mwprop-1.0.10.data/scripts/los_diagnostics.py
mwprop-1.0.10.dist-info/LICENSE.rst
mwprop-1.0.10.dist-info/METADATA
mwprop-1.0.10.dist-info/WHEEL
mwprop-1.0.10.dist-info/top_level.txt
mwprop-1.0.10.dist-info/RECORD
