Metadata-Version: 2.1
Name: mwprop
Version: 1.0.10
Summary: A python package for NE2001
Home-page: https://github.com/stella-ocker/mwprop
Author: James Cordes and Stella Ocker
Author-email: stella.ocker@gmail.com
Project-URL: Bug Tracker, https://github.com/stella-ocker/mwprop/issues
Classifier: Programming Language :: Python :: 3
Classifier: License :: OSI Approved :: GNU General Public License (GPL)
Classifier: Operating System :: OS Independent
Requires-Python: >=3.6
License-File: LICENSE.rst
